README.md
setup.py
base_convertor/__init__.py
base_convertor/main.py
base_convertor.egg-info/PKG-INFO
base_convertor.egg-info/SOURCES.txt
base_convertor.egg-info/dependency_links.txt
base_convertor.egg-info/entry_points.txt
base_convertor.egg-info/top_level.txt