Metadata-Version: 2.1
Name: base_convertor
Version: 0.5.1
Summary: A package for converting numbers from one base to another.
Author: Ajay Maurya
